{"classic-copy-1":{"name":"Classic (Copy)","settings":{"fieldSize":"medium","fieldBorderRadius":"0px","fieldBorderStyle":"solid","fieldBorderSize":"2px","fieldBackgroundColor":"#000000","fieldBorderColor":"#cccccc","fieldTextColor":"#000000","fieldMenuColor":"#ffffff","labelSize":"small","labelColor":"#262626","labelSublabelColor":"#7f7f7f","labelErrorColor":"#ff0000","buttonSize":"medium","buttonBorderStyle":"solid","buttonBorderSize":"1px","buttonBorderRadius":"0px","buttonBorderColor":"#cccccc","buttonBackgroundColor":"#dddddd","buttonTextColor":"#666666","pageBreakColor":"#dddddd"}},"default-copy-1":{"name":"Default (Copy)","settings":{"fieldSize":"small","fieldBorderRadius":"20px","fieldBorderStyle":"solid","fieldBorderSize":"3px","fieldBackgroundColor":"#ffffff","fieldBorderColor":"#ffffff","fieldTextColor":"rgba( 0, 0, 0, 0.7 )","fieldMenuColor":"#000000","labelSize":"medium","labelColor":"#ffffff","labelSublabelColor":"#ffffff","labelErrorColor":"#d63637","buttonSize":"medium","buttonBorderStyle":"solid","buttonBorderSize":"3px","buttonBorderRadius":"20px","buttonBorderColor":"#066aab","buttonBackgroundColor":"#066aab","buttonTextColor":"#ffffff","pageBreakColor":"#066aab"}}}